graycode.v
module sff(
    input s,
    input r,
    input clk,
    input rstn, 
    output reg q,
    output q_bar);
    always @(posedge clk or negedge rstn) begin
        if (!rstn) q <= 0;  
        else if (s && (s^r)) begin
            q<=1;
        end
        else if (r && (s^r)) begin
             q<=0;
        end
        else if (!(s||r)) begin
            q<=q;
        end
    end
    assign q_bar = ~q;
endmodule

module graycode(
    input clk,  
    input [3:0] xin,  
    input rstn,
    output [3:0] out);
    wire  q3, q_bar3;  
    wire  q2, q_bar2;
    wire  q1, q_bar1;
    wire  q0, q_bar0;

    sff sff0 ( .s((~xin[1] && !(xin[2]^xin[3])) || (xin[1] && (xin[2]^xin[3]))),
      .r((~xin[1] && (xin[2]^xin[3])) || ((xin[1] && !(xin[2]^xin[3])))),
      .rstn(rstn),
       .clk(clk), 
       .q(q0),  
       .q_bar(q_bar0));  
  
    sff sff1 ( .s (xin[0] && !(xin[2]^xin[3])),
      .r(xin[0] && (xin[2]^xin[3])),
      .rstn(rstn),
      .clk (clk), 
      .q (q1),  
      .q_bar (q_bar1));
    
    sff sff2 ( .s (~xin[0] && xin[1] && ~xin[3]),
      .r(~xin[0] && xin[1] && xin[3]),
      .rstn(rstn),
      .clk (clk), 
      .q (q2),  
      .q_bar (q_bar2));

    sff sff3 ( .s (~xin[0] && ~xin[1] && xin[2]),
      .r(~xin[0] && ~xin[1] && ~xin[2]),
      .rstn(rstn),
      .clk (clk), 
      .q (q3),  
      .q_bar (q_bar3));
    assign out = {q3 , q2 , q1 , q0};
endmodule

tb_graycode.v
module tb_graycode;  
    reg clk;  
    reg rstn;  
    reg [3:0] xin;
    wire [3:0] out;  
    graycode r0(clk,xin , rstn, out);  
    always #5 clk = ~clk;  
    initial begin
      $dumpfile("graycode.vcd");
	    $dumpvars(0, tb_graycode);
      $monitor($time," %b", out);
      rstn <= 0;  
      clk <= 0;  
      repeat (1) @ (posedge clk); 
      repeat (16) begin
          #10 rstn <= 1;
          #10 xin<=out;   
      end
      $finish;  
   end   
endmodule

graycode.vcd
$date
	Wed May 19 15:15:14 2021
$end
$version
	Icarus Verilog
$end
$timescale
	1s
$end
$scope module tb_graycode $end
$var wire 4 ! out [3:0] $end
$var reg 1 " clk $end
$var reg 1 # rstn $end
$var reg 4 $ xin [3:0] $end
$scope module r0 $end
$var wire 1 " clk $end
$var wire 1 # rstn $end
$var wire 4 % xin [3:0] $end
$var wire 1 & q_bar3 $end
$var wire 1 ' q_bar2 $end
$var wire 1 ( q_bar1 $end
$var wire 1 ) q_bar0 $end
$var wire 1 * q3 $end
$var wire 1 + q2 $end
$var wire 1 , q1 $end
$var wire 1 - q0 $end
$var wire 4 . out [3:0] $end
$scope module sff0 $end
$var wire 1 " clk $end
$var wire 1 ) q_bar $end
$var wire 1 / r $end
$var wire 1 # rstn $end
$var wire 1 0 s $end
$var reg 1 - q $end
$upscope $end
$scope module sff1 $end
$var wire 1 " clk $end
$var wire 1 ( q_bar $end
$var wire 1 1 r $end
$var wire 1 # rstn $end
$var wire 1 2 s $end
$var reg 1 , q $end
$upscope $end
$scope module sff2 $end
$var wire 1 " clk $end
$var wire 1 ' q_bar $end
$var wire 1 3 r $end
$var wire 1 # rstn $end
$var wire 1 4 s $end
$var reg 1 + q $end
$upscope $end
$scope module sff3 $end
$var wire 1 " clk $end
$var wire 1 & q_bar $end
$var wire 1 5 r $end
$var wire 1 # rstn $end
$var wire 1 6 s $end
$var reg 1 * q $end
$upscope $end
$upscope $end
$upscope $end
$enddefinitions $end
#0
$dumpvars
x6
x5
x4
x3
x2
x1
x0
x/
b0 .
0-
0,
0+
0*
1)
1(
1'
1&
bx %
bx $
0#
0"
b0 !
$end
#5
1"
#10
0"
#15
1#
1"
#20
0"
#25
10
0/
15
04
02
01
03
06
b0 $
b0 %
1"
#30
0"
#35
0)
b1 !
b1 .
1-
1"
#40
0"
#45
05
12
b1 $
b1 %
1"
#50
0"
#55
0(
b11 !
b11 .
1,
1"
#60
0"
#65
00
1/
b11 $
b11 %
1"
#70
0"
#75
1)
b10 !
b10 .
0-
1"
#80
0"
#85
14
02
b10 $
b10 %
1"
#90
0"
#95
0'
b110 !
b110 .
1+
1"
#100
0"
#105
10
0/
b110 $
b110 %
1"
#110
0"
#115
0)
b111 !
b111 .
1-
1"
#120
0"
#125
04
11
b111 $
b111 %
1"
#130
0"
#135
1(
b101 !
b101 .
0,
1"
#140
0"
#145
1/
00
b101 $
b101 %
1"
#150
0"
#155
1)
b100 !
b100 .
0-
1"
#160
0"
#165
16
01
b100 $
b100 %
1"
#170
0"
#175
0&
b1100 !
b1100 .
1*
1"
#180
0"
#185
10
0/
b1100 $
b1100 %
1"
#190
0"
#195
0)
b1101 !
b1101 .
1-
1"
#200
0"
#205
06
12
b1101 $
b1101 %
1"
#210
0"
#215
0(
b1111 !
b1111 .
1,
1"
#220
0"
#225
00
1/
b1111 $
b1111 %
1"
#230
0"
#235
1)
b1110 !
b1110 .
0-
1"
#240
0"
#245
13
02
b1110 $
b1110 %
1"
#250
0"
#255
1'
b1010 !
b1010 .
0+
1"
#260
0"
#265
10
0/
b1010 $
b1010 %
1"
#270
0"
#275
0)
b1011 !
b1011 .
1-
1"
#280
0"
#285
03
11
b1011 $
b1011 %
1"
#290
0"
#295
1(
b1001 !
b1001 .
0,
1"
#300
0"
#305
1/
00
b1001 $
b1001 %
1"
#310
0"
#315
1)
b1000 !
b1000 .
0-
1"
#320
0"
#325
15
01
b1000 $
b1000 %
1"
